databouncer-0.1.1.dist-info/METADATA
databouncer-0.1.1.dist-info/WHEEL
databouncer/__init__.py
databouncer/__init__.pyi
databouncer/py.typed
databouncer/databouncer.cp38-win_amd64.pyd
databouncer-0.1.1.dist-info/RECORD
